docsible/__init__.py
docsible/cli.py
docsible/markdown_template.py
docsible/utils/__init__.py
docsible/utils/git.py
docsible/utils/mermaid.py
docsible/utils/special_tasks_keys.py
docsible/utils/yaml.py
docsible-0.8.0.dist-info/LICENSE
docsible-0.8.0.dist-info/METADATA
docsible-0.8.0.dist-info/WHEEL
docsible-0.8.0.dist-info/entry_points.txt
docsible-0.8.0.dist-info/RECORD
